[
  {
    "id": 1,
    "name": "Chrono Cross",
    "imgCover": "/ChronoCross/00-game.jpg",
    "imgBackground": "/ChronoCross/00-background.jpg",
    "text": "Lejos el mejor RPG en mi opinion personal. Precisamente, este juego, me inspiro hacer esta pagina.",
    "source": [
      {
        "name": "Guia",
        "url": "https://guiamania.com/41154/"
      },
      {
        "name": "Window Frame",
        "url": "https://www.ign.com/wikis/chrono-cross/Window_Frames/"
      },
      {
        "name": "Tecnicas",
        "url": "https://guiltybit.com/como-conseguir-las-tecnicas-definitivas-de-todos-los-personajes-en-chrono-cross/"
      },
      {
        "name": "Finales",
        "url": "https://game8.co/games/Chrono-Cross-Radical-Dreamers-Edition/archives/375630/"
      },
      {
        "name": "Items",
        "url": "https://game8.co/games/Chrono-Cross-Radical-Dreamers-Edition/archives/371977"
      }
    ],
    "characters": [
      {
        "id": 1,
        "name": "Serge",
        "text": "Se obtiene al inciar la aventura",
        "img": "/ChronoCross/characters/serge.jpg"
      },
      {
        "id": 2,
        "name": "Mojo",
        "text": "Se obtiene con Shark Tooth Amulet",
        "img": "/ChronoCross/characters/mojo.jpg"
      },
      {
        "id": 3,
        "name": "Leena",
        "text": "Se obtiene rechazando a Kid 3 veces",
        "img": "/ChronoCross/characters/leena.jpg"
      },
      {
        "id": 4,
        "name": "Poshul",
        "text": "Se obtiene rechazando a Kid 3 veces o en Arni Village",
        "img": "/ChronoCross/characters/poshul.jpg"
      },
      {
        "id": 5,
        "name": "Kid",
        "text": "Se obtiene en Termina o Cape Howl",
        "img": "/ChronoCross/characters/kid.jpg"
      },
      {
        "id": 6,
        "name": "Guile",
        "text": "Se obtiene en Termina hablando con él en el bar",
        "img": "/ChronoCross/characters/guile.jpg"
      },
      {
        "id": 7,
        "name": "Nikki",
        "text": "Se obtiene en Termina hablando con Miki en el barco de Magical Dreamers",
        "img": "/ChronoCross/characters/nikki.jpg"
      },
      {
        "id": 8,
        "name": "Pierre",
        "text": "Se obtiene en Termina entregandole el Hero's Medal en la herreria",
        "img": "/ChronoCross/characters/pierre.jpg"
      },
      {
        "id": 9,
        "name": "Glenn",
        "text": "Se obtiene en Termina al decidir No salvar a Kid",
        "img": "/ChronoCross/characters/glenn.jpg"
      },
      {
        "id": 10,
        "name": "Macha",
        "text": "Se obtiene en Termina al decidir No salvar a Kid",
        "img": "/ChronoCross/characters/macha.jpg"
      },
      {
        "id": 11,
        "name": "Greco",
        "text": "Se obtiene en Termina al decidir salvar a Kid",
        "img": "/ChronoCross/characters/greco.jpg"
      },
      {
        "id": 12,
        "name": "Razzly",
        "text": "Se obtiene en Hydra Marsh al decidir salvar a Kid",
        "img": "/ChronoCross/characters/razzly.jpg"
      },
      {
        "id": 13,
        "name": "Mel",
        "text": "Se obtiene en Guldove, despue se capturarla y salir de la isla",
        "img": "/ChronoCross/characters/mel.jpg"
      },
      {
        "id": 34,
        "name": "Fargo",
        "text": "",
        "img": "/sin-personaje.gif"
      },
      {
        "id": 9,
        "name": "Grobyc",
        "text": "",
        "img": "/sin-personaje.gif"
      },
      {
        "id": 10,
        "name": "Lynx",
        "text": "",
        "img": "/sin-personaje.gif"
      },
      {
        "id": 11,
        "name": "Harle",
        "text": "",
        "img": "/sin-personaje.gif"
      },
      {
        "id": 12,
        "name": "Irenes",
        "text": "",
        "img": "/sin-personaje.gif"
      },
      {
        "id": 13,
        "name": "Karsh",
        "text": "",
        "img": "/sin-personaje.gif"
      },
      {
        "id": 14,
        "name": "Korcha",
        "text": "",
        "img": "/sin-personaje.gif"
      },
      {
        "id": 15,
        "name": "Radius",
        "text": "",
        "img": "/sin-personaje.gif"
      },
      {
        "id": 16,
        "name": "Starky",
        "text": "",
        "img": "/sin-personaje.gif"
      },
      {
        "id": 17,
        "name": "Viper",
        "text": "",
        "img": "/sin-personaje.gif"
      },
      {
        "id": 18,
        "name": "Zoah",
        "text": "",
        "img": "/sin-personaje.gif"
      },
      {
        "id": 19,
        "name": "Marcy",
        "text": "",
        "img": "/sin-personaje.gif"
      },
      {
        "id": 20,
        "name": "Riddel",
        "text": "",
        "img": "/sin-personaje.gif"
      },
      {
        "id": 21,
        "name": "Zappa",
        "text": "",
        "img": "/sin-personaje.gif"
      },
      {
        "id": 22,
        "name": "Miki",
        "text": "",
        "img": "/sin-personaje.gif"
      },
      {
        "id": 23,
        "name": "Sprigg",
        "text": "",
        "img": "/sin-personaje.gif"
      },
      {
        "id": 24,
        "name": "Neofio",
        "text": "",
        "img": "/sin-personaje.gif"
      },
      {
        "id": 25,
        "name": "Skelly",
        "text": "",
        "img": "/sin-personaje.gif"
      },
      {
        "id": 26,
        "name": "Van",
        "text": "",
        "img": "/sin-personaje.gif"
      },
      {
        "id": 27,
        "name": "Sneff",
        "text": "",
        "img": "/sin-personaje.gif"
      },
      {
        "id": 28,
        "name": "Pip",
        "text": "",
        "img": "/sin-personaje.gif"
      },
      {
        "id": 29,
        "name": "Luccia",
        "text": "",
        "img": "/sin-personaje.gif"
      },
      {
        "id": 30,
        "name": "Draggy",
        "text": "",
        "img": "/sin-personaje.gif"
      },
      {
        "id": 31,
        "name": "Leah",
        "text": "",
        "img": "/sin-personaje.gif"
      },
      {
        "id": 32,
        "name": "Orlha",
        "text": "",
        "img": "/sin-personaje.gif"
      },
      {
        "id": 33,
        "name": "Norris",
        "text": "",
        "img": "/sin-personaje.gif"
      },
      {
        "id": 37,
        "name": "Janice",
        "text": "",
        "img": "/sin-personaje.gif"
      },
      {
        "id": 38,
        "name": "Turnip",
        "text": "",
        "img": "/sin-personaje.gif"
      },
      {
        "id": 39,
        "name": "Funguy",
        "text": "",
        "img": "/sin-personaje.gif"
      },
      {
        "id": 41,
        "name": "Steena",
        "text": "",
        "img": "/sin-personaje.gif"
      },
      {
        "id": 42,
        "name": "Doc",
        "text": "",
        "img": "/sin-personaje.gif"
      },
      {
        "id": 45,
        "name": "Orcha",
        "text": "",
        "img": "/sin-personaje.gif"
      }
    ],
    "guides": [
      {
        "id": 1,
        "name": "El Sueño",
        "status": false,
        "adventure": [
          {
            "id": 1,
            "text": "✓ Sigue el camino hasta el pilar de luz",
            "important": false,
            "status": false,
            "img": []
          },
          {
            "id": 2,
            "text": "✓ Ponte encima de la plataforma magenta",
            "important": false,
            "status": false,
            "img": []
          },
          {
            "id": 3,
            "text": "✓ Entra por la puerta",
            "important": false,
            "status": false,
            "img": []
          },
          {
            "id": 4,
            "text": "✓ Inicias el juego con estos marcos (Marco 3/15)",
            "important": false,
            "status": false,
            "img": [
              "/ChronoCross/frames/arnian_wood.jpg",
              "/ChronoCross/frames/simple_line.jpg",
              "/ChronoCross/frames/iron_plate.jpg"
            ]
          }
        ]
      },
      {
        "id": 2,
        "name": "Final oculto: Programmer's Ending (Final 1/12)",
        "status": false,
        "adventure": [
          {
            "id": 1,
            "text": "✓ Cuando despiertes crea un guardado independiente de la partida principal, cuando termines el juego carga esta partida con el Continue+ (NO con el NG+). Vencer al 'Time Devourer' inmediatamente sin reclutar compañeros.",
            "important": true,
            "status": false,
            "img": [
              "/ChronoCross/adventure/arni_village_01.jpg"
            ]
          }
        ]
      },
      {
        "id": 3,
        "name": "(HW) Arni Village",
        "status": false,
        "adventure": [
          {
            "id": 1,
            "text": "✓ Despiertas con Serge (Personaje 1/46)",
            "important": false,
            "status": false,
            "img": []
          },
          {
            "id": 2,
            "text": "✓ Habla con Marge (Mamá)",
            "important": false,
            "status": false,
            "img": []
          },
          {
            "id": 3,
            "text": "✓ Ve al puerto y habla con Leena",
            "important": false,
            "status": false,
            "img": []
          },
          {
            "id": 4,
            "text": "✓ Coge la Shellfish Window Frame de la tienda de elements (Marco 4/15)",
            "important": false,
            "status": false,
            "img": [
              "/ChronoCross/adventure/arni_village_02.jpg",
              "/ChronoCross/frames/shellfish.jpg"
            ]
          },
          {
            "id": 5,
            "text": "✓ Coge el Shark Tooth Amulet de uno de los tipos de las casas de la derecha (Item 1/57)",
            "important": false,
            "status": false,
            "img": [
              "/ChronoCross/adventure/arni_village_03.jpg",
              "/ChronoCross/items/shark_tooth.jpg"
            ]
          },
          {
            "id": 6,
            "text": "✓ Consigue un Hueso Heckran de debajo de la cama del bar (Item 2/57)",
            "important": false,
            "status": false,
            "img": [
              "/ChronoCross/adventure/arni_village_04.jpg",
              "/ChronoCross/items/heckran.jpg"
            ]
          },
          {
            "id": 7,
            "text": "✓ 'NO' reclutes a Poshul aún",
            "important": false,
            "status": false,
            "img": []
          }
        ]
      },
      {
        "id": 4,
        "name": "(HW) Lizard Rock",
        "status": false,
        "adventure": [
          {
            "id": 1,
            "text": "✓ Empuja la roca enfrente de la cueva, y lucha con el primer Komodo",
            "important": false,
            "status": false,
            "img": [
              "/ChronoCross/adventure/lizard_rock_01.jpg"
            ]
          },
          {
            "id": 2,
            "text": "✓ Usa el saliente para llegar el segundo Komodo",
            "important": false,
            "status": false,
            "img": [
              "/ChronoCross/adventure/lizard_rock_02.jpg"
            ]
          },
          {
            "id": 3,
            "text": "✓ Debes perseguir, para cazar y luego luchar con el tercer Komodo, y luego a Mamá Komodo",
            "important": false,
            "status": false,
            "img": [
              "/ChronoCross/adventure/lizard_rock_03.jpg"
            ]
          },
          {
            "id": 4,
            "text": "✓ Sal por la izquierda de la playa, y sigue recto…",
            "important": false,
            "status": false,
            "img": []
          }
        ]
      },
      {
        "id": 5,
        "name": "(AW) Another World",
        "status": false,
        "adventure": [
          {
            "id": 1,
            "text": "✓ Ve a Arni y habla con Marge y Leena",
            "important": false,
            "status": false,
            "img": []
          },
          {
            "id": 2,
            "text": "✓ Ve donde conseguiste el Shark Tooth Amulet para coger a Mojo (Personaje 2/46)",
            "important": false,
            "status": false,
            "img": [
              "/ChronoCross/adventure/another_world_01.jpg",
              "/ChronoCross/adventure/another_world_02.jpg"
            ]
          },
          {
            "id": 3,
            "text": "✓ Ve a Cape Howl y examina la tumba",
            "important": false,
            "status": false,
            "img": []
          },
          {
            "id": 4,
            "text": "✓ Lucharás con Karsh, Solt y Peppor",
            "important": false,
            "status": false,
            "img": []
          },
          {
            "id": 5,
            "text": "✓ Nombra a Kid pero NO la reclutes aún (rechaza 3 veces)",
            "important": false,
            "status": false,
            "img": []
          },
          {
            "id": 6,
            "text": "✓ Leena y Poshul se te unirán ahora (es la única manera de conseguir a Leena) (Personaje 4/46)",
            "important": false,
            "status": false,
            "img": []
          },
          {
            "id": 7,
            "text": "✓ Con cualquiera de los personajes, ve al Hydra Swamp (Pantano de la Hydra)",
            "important": false,
            "status": false,
            "img": []
          }
        ]
      },
      {
        "id": 6,
        "name": "(AW) Hydra Swamp",
        "status": false,
        "adventure": [
          {
            "id": 1,
            "text": "✓ Ve al noroeste, encuentra a un chico que te dará un traje para lo radiactivo (Item 3/57)",
            "important": false,
            "status": false,
            "img": [
              "/ChronoCross/adventure/hydra_swamp_01.jpg",
              "/ChronoCross/items/safety_gear.jpg"
            ]
          },
          {
            "id": 2,
            "text": "✓ Vete por ahora al Fossil Valley",
            "important": false,
            "status": false,
            "img": []
          }
        ]
      },
      {
        "id": 7,
        "name": "(AW) Fossil Valley",
        "status": false,
        "adventure": [
          {
            "id": 1,
            "text": "✓ Obten el craneo para un personaje que se llama Skelly (Item 4/57)",
            "important": false,
            "status": false,
            "img": [

            ]
          },
          {
            "id": 2,
            "text": "✓ Obten las Bellflowers y el huevo gigante (cerca del pájaro) (Item 6/57)",
            "important": false,
            "status": false,
            "img": []
          },
          {
            "id": 3,
            "text": "✓ Continua el camino hacia el norte y lucha contra Solt y Peppor",
            "important": false,
            "status": false,
            "img": []
          }
        ]
      },
      {
        "id": 8,
        "name": "(AW) Termina",
        "status": false,
        "adventure": [
          {
            "id": 1,
            "text": "✓ Ve a la estatua en lo más alto del pueblo, y consigue a Kid (Personaje 5/46)",
            "important": false,
            "status": false,
            "img": []
          },
          {
            "id": 2,
            "text": "✓ Obten el marco Tea for Three (Marco 5/15)",
            "important": false,
            "status": false,
            "img": [
              "/ChronoCross/frames/tea_for_three.jpg"
            ]
          },
          {
            "id": 3,
            "text": "✓ Ve a la parte más al este del pueblo, dale las flores a Glenn",
            "important": false,
            "status": false,
            "img": []
          },
          {
            "id": 4,
            "text": "✓ Aqui debes decidir cual de los 3 personajes quieres reclutar para infiltrarte en el Viper Manor, No los puedes conseguir a todos en una partida, deberas iniciar una partida (NG+) para los 2 que falten.",
            "important": false,
            "status": false,
            "img": []
          },
          {
            "id": 5,
            "text": "✓ Opción 1: Consigue a Guile (Personaje 6/46), Habla con él en el bar. Ve al puerto de Termina, encuentra el barco de Korcha y sube por el rompeolas",
            "important": true,
            "status": false,
            "img": []
          },
          {
            "id": 6,
            "text": "✓ Opción 2: Consigue a Nikki (Personaje 7/46), habla con Miki en el barco de Magical Dreamers. Ve al Bosque Shadow, consigue la Aroma Bag (Item 7/57) y úsalo para mover a los monstruitos hacia el monstruo-planta gigante, en la cueva puedes encontrar el Skullduggery (Marco /15), avanza por el camino que bloqueaba el mounstruo hasta salir por el pozo",
            "important": true,
            "status": false,
            "img": [
              "/ChronoCross/items/aroma_pouch.jpg",
              "/ChronoCross/frames/skullduggery.jpg"
            ]
          },
          {
            "id": 7,
            "text": "✓ Opción 3: Consigue a Pierre (Personaje 8/46), en la Herrería, primero debes conseguir el Hero's Medal (Item 8/57) del del niño que juega afuera, Ve a la puerta principal de Viper Manor",
            "important": true,
            "status": false,
            "img": []
          }
        ]
      },
      {
        "id": 9,
        "name": "Final oculto: General Kid (Final 2/12)",
        "status": false,
        "adventure": [
          {
            "id": 1,
            "text": "✓ Crea un guardado independiente de la partida principal, cuando termines el juego carga esta partida con el Continue+ (NO con el NG+). Vencer al 'Time Devourer' antes de infiltrarte en Viper Manor",
            "important": true,
            "status": false,
            "img": []
          }
        ]
      },
      {
        "id": 10,
        "name": "(AW) Infiltración a Viper Manor",
        "status": false,
        "adventure": [
          {
            "id": 1,
            "text": "✓ La puerta principal está cerrada",
            "important": false,
            "status": false,
            "img": []
          },
          {
            "id": 2,
            "text": "✓ La llave Manor Key (Item 9/57) está en la parte superior derecha del establo de alimentación de dragones",
            "important": false,
            "status": false,
            "img": [
              "/ChronoCross/items/manor_key.jpg"
            ]
          },
          {
            "id": 3,
            "text": "✓ Debes jugar al juego de alimentar dragones al menos una vez, si quieres alimentarlos todos sin fallar, puedes usar el Time Shifter (Item 10/57) que puedes obtener en la partida (NG+)",
            "important": false,
            "status": false,
            "img": [
              "/ChronoCross/items/time_shifter.jpg"
            ]
          }
        ]
      },
      {
        "id": 11,
        "name": "(AW) Viper Manor",
        "status": false,
        "adventure": [
          {
            "id": 1,
            "text": "✓ Gira la estatua de la serpiente, y cae en la trampa",
            "important": false,
            "status": false,
            "img": []
          },
          {
            "id": 2,
            "text": "✓ Lucha con los guardias, coge su ropa y entra en las habitaciones de la parte izquierda",
            "important": false,
            "status": false,
            "img": []
          },
          {
            "id": 3,
            "text": "✓ En la cocina, habla con Glenn, ve a su habitación, y te escribirá la combinación de la estatua",
            "important": false,
            "status": false,
            "img": []
          },
          {
            "id": 4,
            "text": "✓ En las habitaciones de la derecha, intenta coger el pendiente y cae en otra trampa",
            "important": false,
            "status": false,
            "img": []
          },
          {
            "id": 5,
            "text": "✓ Lucha con los bichos de Luccia",
            "important": false,
            "status": false,
            "img": []
          },
          {
            "id": 6,
            "text": "✓ Vuelve a la entrada y usa la combinación apropiada en la estatua de la serpiente",
            "important": false,
            "status": false,
            "img": []
          },
          {
            "id": 7,
            "text": "✓ Ve al oeste, a la biblioteca, verás a Balthasar (Chrono Trigger), lucha con Marcy",
            "important": false,
            "status": false,
            "img": []
          },
          {
            "id": 8,
            "text": "✓ Habla con el viejo, vuelve a la habitación grande, busca en las columnas un botón que accione el ascensor",
            "important": false,
            "status": false,
            "img": []
          },
          {
            "id": 9,
            "text": "✓ Obten el marco Porre's Furnace (Marco 6/15)",
            "important": false,
            "status": false,
            "img": [
              "/ChronoCross/frames/porres_furnace.jpg"
            ]
          },
          {
            "id": 10,
            "text": "✓ Lucha con los guardias, toma el ascensor y para la puerta derecha",
            "important": false,
            "status": false,
            "img": []
          },
          {
            "id": 11,
            "text": "✓ Lucha contra Lynx, habrá unas cuantas escenas",
            "important": false,
            "status": false,
            "img": []
          }
        ]
      },
      {
        "id": 12,
        "name": "Final oculto: The True Hero (Final 3/12)",
        "status": false,
        "adventure": [
          {
            "id": 1,
            "text": "✓ Este final tiene 2 variantes, las variantes dependeran de que decisión tomas en Guldove.",
            "important": false,
            "status": false,
            "img": []
          },
          {
            "id": 2,
            "text": "✓ Opcion 1: No salvar a Kid. Crea un guardado independiente de la partida principal, cuando termines el juego carga esta partida con el Continue+ (NO con el NG+), Vencer al 'Time Devourer' inmediatamente despues de que Kid quede envenenada",
            "important": true,
            "status": false,
            "img": []
          },
          {
            "id": 3,
            "text": "✓ Opcion 2: Salvar a Kid con la cura encontrada en Hydra Marsh. Crea un guardado independiente de la partida principal, cuando termines el juego carga esta partida con el Continue+ (NO con el NG+), Vencer al 'Time Devourer' inmediatamente despues de que Kid se haya curado",
            "important": true,
            "status": false,
            "img": []
          }
        ]
      },
      {
        "id": 13,
        "name": "(AW) Guldove",
        "status": false,
        "adventure": [
          {
            "id": 1,
            "text": "✓ Consigue la parte del pelvis de Skelly (Item /57) de la niña comerciante cerca del barco",
            "important": false,
            "status": false,
            "img": []
          },
          {
            "id": 2,
            "text": "✓ Tendras que eleguir entre salvar o NO salvar a kid, dependiendo de la decicion podras obtener nuevos personajes distintos en ambos casos",
            "important": false,
            "status": false,
            "img": []
          },
          {
            "id": 3,
            "text": "✓ Opcion 1: No salvar a Kid: Habla con Macha y todo el mundo en Guldove, toma el barco de Kocha hacia Termina, en la entrada verás a Glenn. Vuelve al barco, conseguirás a Glenn y Macha (Personaje 9 y 10/46), Macha te dara el Tropical Paradise (Marco 7/15), ve al mar nublado al este de El Nido y haz el capítulo Piratas Fantasmas luego vuelve a Guldove para ver al Doc y Kid.",
            "important": true,
            "status": false,
            "img": [
              "/ChronoCross/frames/tropical_paradise.jpg"
            ]
          },
          {
            "id": 4,
            "text": "✓ Opcion 2: Salvar a Kid: Toma el barco hacia Termina, pero consigue a Greco (Personaje 11/46) en la casa del cementerio en Termina, Ve a la Playa Opassa, usa el Astral Amulet (Item /57) de Kid en el agujero para volver a Home World, Ve al Hydra Marsh, lucha con Beeba, coge la flauta (Item /57) y úsala al norte de todo, Lucha contra el Wingapede, luego con el pulpo y consigue a Razzly el hada (Personaje 12/46), sigue luego por la parte este, lucha contra la Hydra, obtendras la medicina ahora vuelve a Guldove, asegúrate de cazar a Mel (Personaje 13/46) si la quieres conseguir más tarde y ella te da el Guldovian Stitch (Marco 8/15), finalmente conseguiras a Kid. Capítulo Piratas Fantasmas",
            "important": true,
            "status": false,
            "img": [
              "/ChronoCross/items/astral_amulet.jpg",
              "/ChronoCross/items/beeba_flute.jpg",
              "/ChronoCross/frames/guldovian_stitch.jpg"
            ]
          }
        ]
      },
      {
        "id": 14,
        "name": "(AW) Piratas Fantasmas",
        "status": false,
        "adventure": [
          {
            "id": 1,
            "text": "✓ Holy Porfiad(@)",
            "important": false,
            "status": false,
            "img": []
          }
        ]
      }
    ]
  },
  {
    "id": 2,
    "name": "Comrades",
    "imgCover": "/Comrades/00-game.png",
    "imgBackground": "/Comrades/00-background.jpg",
    "text": "Creo que soy el único que juega a esto, los servidores siempre están vacíos.",
    "characters": [],
    "source": [],
    "guides": [
      {
        "id": 1,
        "name": "Sin Guia",
        "status": false,
        "adventure": [
          {
            "id": 1,
            "text": "✓ Holy Porfiad(@)",
            "important": false,
            "status": false,
            "img": []
          }
        ]
      }
    ]
  },
  {
    "id": 3,
    "name": "Darksiders 2",
    "imgCover": "/Darksiders2/00-game.jpg",
    "imgBackground": "/Darksiders2/00-background.jpg",
    "text": "Un MANJAR de los dioses",
    "characters": [],
    "source": [],
    "guides": []
  }
]